{
  "name": "Operate",
  "props": [
    {
      "displayName": "data",
      "type": "object",
      "description": "操作项数据配置",
      "defaultValue": "",
      "tip": "OperateData[]"
    },
    {
      "displayName": "total",
      "type": "number",
      "description": "选中数据总数",
      "defaultValue": ""
    },
    {
      "displayName": "max",
      "type": "number",
      "description": "显示操作按钮的最大数量",
      "defaultValue": "4"
    },
    {
      "displayName": "hide-on-click",
      "type": "boolean",
      "description": "点击下拉菜单后是否隐藏下拉菜单",
      "defaultValue": "true"
    }
  ],
  "events": [
    {
      "displayName": "close",
      "description": "点击关闭按钮时触发",
      "type": "Function",
      "tip": "() => void"
    }
  ],
  "slots": [],
  "methods": []
}